drflickr/__init__.py
drflickr/api.py
drflickr/applicator.py
drflickr/applicator_greylist.py
drflickr/blacklist_updater.py
drflickr/cli/__init__.py
drflickr/cli/access_token.py
drflickr/cli/automation.py
drflickr/cli/main.py
drflickr/cli/path_options.py
drflickr/credentials.py
drflickr/file.py
drflickr/greylist.py
drflickr/group_checker.py
drflickr/group_info.py
drflickr/group_info_updater.py
drflickr/group_selector.py
drflickr/list_ordering.py
drflickr/logic.py
drflickr/operations_review.py
drflickr/photoset.py
drflickr/publisher.py
drflickr/reconciler.py
drflickr/reorderer.py
drflickr/retriever.py
drflickr/runner.py
drflickr/stats.py
drflickr/submissions.py
drflickr-0.3.6.dist-info/LICENSE
drflickr-0.3.6.dist-info/METADATA
drflickr-0.3.6.dist-info/WHEEL
drflickr-0.3.6.dist-info/entry_points.txt
drflickr-0.3.6.dist-info/RECORD
